ultoical/__init__.py
ultoical/__main__.py
ultoical/gui.py
ultoical/ical_handler.py
ultoical/ul_handler.py
ultoical-1.1.2.dist-info/LICENSE
ultoical-1.1.2.dist-info/METADATA
ultoical-1.1.2.dist-info/WHEEL
ultoical-1.1.2.dist-info/entry_points.txt
ultoical-1.1.2.dist-info/top_level.txt
ultoical-1.1.2.dist-info/RECORD
