Metadata-Version: 2.2
Name: ultoical
Version: 1.1.2
Summary: A web app allowing you to create an ical file from your Universite de Lorraine's timetable
Home-page: https://github.com/totorocodesoften/ultoical
Author: totorocodesoften
Author-email: totorocodesoften@github.com
Classifier: Programming Language :: Python :: 3
Classifier: License :: OSI Approved :: GNU General Public License v3 (GPLv3)
Classifier: Operating System :: OS Independent
Requires-Python: >=3.10
License-File: LICENSE
Requires-Dist: setuptools~=75.8.0
Requires-Dist: gradio~=5.13.1
Requires-Dist: requests~=2.32.3
Dynamic: author
Dynamic: author-email
Dynamic: classifier
Dynamic: description
Dynamic: description-content-type
Dynamic: home-page
Dynamic: requires-dist
Dynamic: requires-python
Dynamic: summary
